open_gemini/__init__.py
open_gemini-0.0.0.dist-info/METADATA
open_gemini-0.0.0.dist-info/WHEEL
open_gemini-0.0.0.dist-info/top_level.txt
open_gemini-0.0.0.dist-info/RECORD
